vimanager/__init__.py
vimanager/__main__.py
vimanager/models.py
vimanager/py.typed
vimanager/utils.py
vimanager/cli/__init__.py
vimanager/cli/edit.py
vimanager/cli/inspector.py
vimanager/cli/sorter.py
vimanager/cli/download/__init__.py
vimanager/cli/download/ffmpeg.py
vimanager/cli/download/metadata.py
vimanager/cli/spotify/__init__.py
vimanager/cli/spotify/http.py
vimanager/cli/spotify/matching.py
vimanager/cli/spotify/models.py
vimanager_cli-0.2.0.dist-info/LICENSE
vimanager_cli-0.2.0.dist-info/METADATA
vimanager_cli-0.2.0.dist-info/WHEEL
vimanager_cli-0.2.0.dist-info/entry_points.txt
vimanager_cli-0.2.0.dist-info/top_level.txt
vimanager_cli-0.2.0.dist-info/RECORD
