Metadata-Version: 2.1
Name: vimanager-cli
Version: 0.2.0
Summary: An unofficial ViMusic CLI that enhances playlist management.
Home-page: https://github.com/Lee-matod/vimanager-cli
Author: Lee-matod
License: MIT
Project-URL: Issue Tracker, https://github.com/Lee-matod/vimanager-cli/issues
Classifier: Intended Audience :: Developers
Classifier: License :: OSI Approved :: MIT License
Classifier: Natural Language :: English
Classifier: Operating System :: OS Independent
Classifier: Programming Language :: Python :: 3.8
Classifier: Programming Language :: Python :: 3.9
Classifier: Programming Language :: Python :: 3.10
Classifier: Topic :: Database
Classifier: Topic :: Terminals
Classifier: Topic :: Utilities
Classifier: Typing :: Typed
Requires-Python: >=3.8.0
License-File: LICENSE
Requires-Dist: Click >=8.0.0
Requires-Dist: colorama >=0.4.0
Provides-Extra: download
Requires-Dist: mutagen ; extra == 'download'
Requires-Dist: yt-dlp ; extra == 'download'
Provides-Extra: full
Requires-Dist: mutagen ; extra == 'full'
Requires-Dist: yt-dlp ; extra == 'full'
Requires-Dist: rapidfuzz ; extra == 'full'
Requires-Dist: ytmusicapi ; extra == 'full'
Provides-Extra: spotify
Requires-Dist: rapidfuzz ; extra == 'spotify'
Requires-Dist: ytmusicapi ; extra == 'spotify'
